lunarcrush/__init__.py
lunarcrush/cache.py
lunarcrush/client.py
lunarcrush/converter.py
lunarcrush/provider.py
lunarcrush_provider-1.0.6.dist-info/METADATA
lunarcrush_provider-1.0.6.dist-info/WHEEL
lunarcrush_provider-1.0.6.dist-info/top_level.txt
lunarcrush_provider-1.0.6.dist-info/RECORD
