Metadata-Version: 2.4
Name: lunarcrush-provider
Version: 1.0.6
Summary: LunarCrush sentiment data provider
Project-URL: repository, https://codeberg.org/5queezer/lunarcrush
Requires-Python: >=3.8
Requires-Dist: pandas>=1.5.0
Requires-Dist: numpy>=1.21.0
Requires-Dist: requests>=2.25.0
Provides-Extra: test
Requires-Dist: pytest>=7.0.0; extra == "test"
Requires-Dist: pytest-cov>=4.0.0; extra == "test"
Requires-Dist: pytest-mock>=3.10.0; extra == "test"
